{
    "rcp0": {
        "input": {
            "橡树木头": 4
        },
        "output": {
            "工作台": 1
        },
        "time": 5000
    },
    "rcp1": {
        "input": {
            "铁": 1,
            "锡": 1,
            "铜": 1
        },
        "mid": "工作台",
        "output": {
            "基础电子电路": 1
        }
    },
    "rcp2": {
        "input": {
            "基础电子电路": 1,
            "锡": 2
        },
        "mid": "工作台",
        "output": {
            "优质电子电路": 1
        }
    },
    "rcp3": {
        "input": {
            "锡": 1
        },
        "mid": "工作台",
        "output": {
            "单晶硅": 1
        }
    }
}